beetsplug/__init__.py
beetsplug/webm3u/__init__.py
beetsplug/webm3u/playlist.py
beetsplug/webm3u/routes.py
beetsplug/webm3u/static/style.css
beetsplug/webm3u/templates/files.html
beetsplug/webm3u/templates/index.html
beetsplug/webm3u/templates/playlists.html
beets_webm3u-0.6.5.dist-info/LICENSE
beets_webm3u-0.6.5.dist-info/METADATA
beets_webm3u-0.6.5.dist-info/WHEEL
beets_webm3u-0.6.5.dist-info/top_level.txt
beets_webm3u-0.6.5.dist-info/RECORD
