Metadata-Version: 2.1
Name: beets-webm3u
Version: 0.6.5
Summary: Serve M3U playlists via HTTP
Home-page: https://github.com/mgoltzsche/beets-webm3u
Author: Max Goltzsche
License: UNKNOWN
Platform: UNKNOWN
Classifier: Programming Language :: Python :: 3.6
Classifier: License :: OSI Approved :: MIT License
Classifier: Operating System :: OS Independent
License-File: LICENSE
Requires-Dist: beets
